{
  "name": "nexsale-button-bordered-secondary",
  "type": "registry:example",
  "registryDependencies": [
    "button"
  ],
  "files": [
    {
      "path": "examples/nexsale/button-bordered-secondary.tsx",
      "content": "import { Button } from \"@/registry/new-york/ui/button\"\n\nexport default function ButtonBorderedSecondary() {\n  return (\n    <Button nexsale bordered variant=\"secondary\">\n      Secondary\n    </Button>\n  )\n}\n",
      "type": "registry:example",
      "target": ""
    }
  ]
}